my_library/__init__.py
my_library/data_processing/__init__.py
my_library/data_processing/clean.py
my_library/data_processing/transform.py
my_library/google_translate/__init__.py
my_library/google_translate/client.py
my_library/google_translate/utils.py
tests/__init__.py
tests/test_client.py
python_pip_2-1.0.0.dist-info/METADATA
python_pip_2-1.0.0.dist-info/WHEEL
python_pip_2-1.0.0.dist-info/top_level.txt
python_pip_2-1.0.0.dist-info/RECORD
