Metadata-Version: 2.1
Name: python_pip_2
Version: 1.0.0
Summary: A small example package
Home-page: https://git.e-science.pl/barmil6059/python_pip
Author: barmil6059
Author-email: barmil6059 <264164@student.pwr.edu.pl>
Project-URL: PyPI, https://upload.pypi.org/legacy/
Classifier: Programming Language :: Python :: 3
Classifier: License :: OSI Approved :: MIT License
Classifier: Operating System :: OS Independent
Requires-Python: >=3.6
